fastapi_enhance/__init__.py
fastapi_enhance/enhance.py
fastapi_enhance/openapi/css/swagger-ui.css
fastapi_enhance/openapi/js/redoc.standalone.js
fastapi_enhance/openapi/js/swagger-ui-bundle.js
fastapi_enhance-1.0.0.dist-info/licenses/LICENSE
fastapi_enhance-1.0.0.dist-info/METADATA
fastapi_enhance-1.0.0.dist-info/WHEEL
fastapi_enhance-1.0.0.dist-info/top_level.txt
fastapi_enhance-1.0.0.dist-info/RECORD
