Metadata-Version: 2.4
Name: fastapi-enhance
Version: 1.0.0
Summary: The extended function library of fastapi can be read README.md
Home-page: https://github.com/hgz1989/fastapi-enhance
Author: HanGuangZheng
Author-email: hanguangzheng@qq.com
Classifier: Programming Language :: Python :: 3
Classifier: License :: OSI Approved :: MIT License
Classifier: Operating System :: OS Independent
Requires-Python: >=3.8
License-File: LICENSE
Requires-Dist: fastapi>=0.111.0
Dynamic: license-file
